code/__init__.py
code/pch125lib.py
pch125lib-0.0.4.2.dist-info/LICENSE.txt
pch125lib-0.0.4.2.dist-info/METADATA
pch125lib-0.0.4.2.dist-info/WHEEL
pch125lib-0.0.4.2.dist-info/top_level.txt
pch125lib-0.0.4.2.dist-info/RECORD
