Metadata-Version: 2.1
Name: pch125lib
Version: 0.0.4.2
Summary: Thư viện này là một bộ sưu tập hàm con của mình
Home-page: https://github.com/Joesifer/pch125lib_
Author: PCH_125
Author-email: phanchanhung12055@gmail.com
Requires-Python: >=3.7
License-File: LICENSE.txt
Requires-Dist: numpy
Requires-Dist: roman
